promptflow/parallel/__init__.py
promptflow/parallel/_config/__init__.py
promptflow/parallel/_config/model.py
promptflow/parallel/_config/parser.py
promptflow/parallel/_executor/__init__.py
promptflow/parallel/_executor/base.py
promptflow/parallel/_executor/bulk_executor.py
promptflow/parallel/_executor/component_executor.py
promptflow/parallel/_executor/input_mapping.py
promptflow/parallel/_metrics/__init__.py
promptflow/parallel/_metrics/metrics.py
promptflow/parallel/_metrics/sender.py
promptflow/parallel/_model.py
promptflow/parallel/_processor/__init__.py
promptflow/parallel/_processor/aggregation_finalizer.py
promptflow/parallel/_processor/base.py
promptflow/parallel/_processor/bulk_processor.py
promptflow/parallel/_processor/component_processor.py
promptflow/parallel/_processor/debug_info.py
promptflow/parallel/_processor/finalizer.py
promptflow/parallel/_version.py
promptflow/parallel/processor.py
promptflow/parallel/utils.py
promptflow_parallel-0.1.0.dist-info/METADATA
promptflow_parallel-0.1.0.dist-info/WHEEL
promptflow_parallel-0.1.0.dist-info/RECORD
