Metadata-Version: 2.1
Name: promptflow-parallel
Version: 0.1.0
Summary: Prompt flow parallel computing
Home-page: https://microsoft.github.io/promptflow/
License: MIT
Keywords: parallel computing
Author: Microsoft Corporation
Author-email: aml-pt-eng@microsoft.com
Requires-Python: >=3.8,<4.0
Classifier: License :: OSI Approved :: MIT License
Classifier: Operating System :: OS Independent
Classifier: Programming Language :: Python
Classifier: Programming Language :: Python :: 3
Classifier: Programming Language :: Python :: 3.8
Classifier: Programming Language :: Python :: 3.9
Classifier: Programming Language :: Python :: 3.10
Classifier: Programming Language :: Python :: 3.11
Classifier: Programming Language :: Python :: 3.12
Classifier: Programming Language :: Python :: 3 :: Only
Requires-Dist: promptflow-core (<2.0.0)
Project-URL: Bug Reports, https://github.com/microsoft/promptflow/issues
Project-URL: Repository, https://github.com/microsoft/promptflow
